seCore/ConfigSettings.py
seCore/CustomLogging.py
seCore/Encryption.py
seCore/Exceptions.py
seCore/HttpRest.py
seCore/ProjectRoot.py
seCore/PyVersions.py
seCore/__about__.py
seCore/__init__.py
seCore/jsondb/__init__.py
seCore/jsondb/_version.py
seCore/jsondb/db.py
seCore/jsondb/db_types.py
seCore/jsondb/errors.py
seCore/templates/ConfigSettings.py
seCore/templates/__init__.py
secore-2025.6.0.dist-info/METADATA
secore-2025.6.0.dist-info/WHEEL
secore-2025.6.0.dist-info/top_level.txt
secore-2025.6.0.dist-info/RECORD
