Metadata-Version: 2.4
Name: seCore
Version: 2025.6.0
Summary: High-performance secure core framework for scalable, reliable applications
Author-email: Cybernetic Innovations <github@cyberneticinnovations.com>
License: MIT License
Classifier: License :: OSI Approved :: MIT License
Requires-Python: >=3.10
Requires-Dist: PyYAML~=6.0.2
Requires-Dist: cryptography~=45.0.3
Requires-Dist: loguru~=0.7.3
Requires-Dist: pydantic~=2.11.5
Requires-Dist: requests~=2.32.3
Requires-Dist: urllib3~=2.4.0
Requires-Dist: beautifulsoup4
Requires-Dist: bitflags~=1.1.3
